sne4onnx/__init__.py
sne4onnx/__main__.py
sne4onnx/onnx_network_extraction.py
sne4onnx-1.0.15.dist-info/licenses/LICENSE
sne4onnx-1.0.15.dist-info/METADATA
sne4onnx-1.0.15.dist-info/WHEEL
sne4onnx-1.0.15.dist-info/entry_points.txt
sne4onnx-1.0.15.dist-info/top_level.txt
sne4onnx-1.0.15.dist-info/RECORD
